main.py
main_silverbullion.py
bullion/__init__.py
bullion/BullionStar/__init__.py
bullion/BullionStar/models/InitializedOrder.py
bullion/SilverBullion/__init__.py
bullion/StarGrams/__init__.py
singapore_bullion_retailers-0.0.6.dist-info/LICENSE
singapore_bullion_retailers-0.0.6.dist-info/METADATA
singapore_bullion_retailers-0.0.6.dist-info/WHEEL
singapore_bullion_retailers-0.0.6.dist-info/top_level.txt
singapore_bullion_retailers-0.0.6.dist-info/RECORD
