Metadata-Version: 2.1
Name: singapore_bullion_retailers
Version: 0.0.6
Summary: A package for accessing Singapore bullion retailers API
Author-email: Chad Lim Jin Jie <chadlimjinjie@gmail.com>
Project-URL: Homepage, https://github.com/chadlimjinjie/singapore_bullion_retailers
Project-URL: Issues, https://github.com/chadlimjinjie/singapore_bullion_retailers/issues
Classifier: Programming Language :: Python :: 3
Classifier: License :: OSI Approved :: MIT License
Classifier: Operating System :: OS Independent
Requires-Python: >=3.8
License-File: LICENSE
